{"cameraMode":{"drawMode":0,"name":"Shaded","section":"Shading Mode"},"sceneLighting":true,"audioPlay":false,"sceneViewState":{"m_AlwaysRefresh":false,"showFog":true,"showSkybox":true,"showFlares":true,"showImageEffects":true,"showParticleSystems":true,"showVisualEffectGraphs":true,"m_FxEnabled":true},"in2DMode":false,"pivot":{"x":7.434595584869385,"y":-9.236270904541016,"z":9.011978149414063},"rotation":{"x":-0.26291900873184206,"y":-0.1858764886856079,"z":0.05329172685742378,"w":-0.9454306960105896},"size":11.198882102966309,"orthographic":false}